pip_upgrade_outdated/__init__.py
pip_upgrade_outdated/__main__.py
pip_upgrade_outdated/upgrade_pip_packages.py
pip_upgrade_outdated-1.5.dist-info/LICENSE
pip_upgrade_outdated-1.5.dist-info/METADATA
pip_upgrade_outdated-1.5.dist-info/WHEEL
pip_upgrade_outdated-1.5.dist-info/entry_points.txt
pip_upgrade_outdated-1.5.dist-info/top_level.txt
pip_upgrade_outdated-1.5.dist-info/RECORD
