Metadata-Version: 2.1
Name: pip-upgrade-outdated
Version: 1.5
Summary: Command-line tool to updated outdated python packages
Home-page: http://github.com/defjaf/pip_upgrade_outdated
Author: Andrew H. Jaffe
Author-email: a.h.jaffe@gmail.com
License: MIT
Keywords: pip
Platform: UNKNOWN
Classifier: Development Status :: 5 - Production/Stable
Classifier: Intended Audience :: Developers
Classifier: Intended Audience :: System Administrators
Classifier: Topic :: Software Development :: Build Tools
Classifier: Topic :: Software Development :: Libraries :: Python Modules
Classifier: Topic :: System :: Archiving :: Packaging
Classifier: License :: OSI Approved :: MIT License
Classifier: Programming Language :: Python :: 2
Classifier: Programming Language :: Python :: 3
Requires-Dist: pip
